CHANGELOG.rst
CONTRIBUTING.rst
MANIFEST.in
README.rst
requirements.txt
setup.cfg
setup.py
opps/__init__.py
opps/urls.py
opps.egg-info/PKG-INFO
opps.egg-info/SOURCES.txt
opps.egg-info/dependency_links.txt
opps.egg-info/namespace_packages.txt
opps.egg-info/not-zip-safe
opps.egg-info/requires.txt
opps.egg-info/top_level.txt
opps/api/__init__.py
opps/api/admin.py
opps/api/conf.py
opps/api/models.py
opps/api/urls.py
opps/api/migrations/0001_initial.py
opps/api/migrations/__init__.py
opps/archives/__init__.py
opps/archives/admin.py
opps/archives/models.py
opps/archives/migrations/0001_initial.py
opps/archives/migrations/0002_auto__add_field_file_archive_link__chg_field_file_archive.py
opps/archives/migrations/__init__.py
opps/articles/__init__.py
opps/articles/admin.py
opps/articles/forms.py
opps/articles/models.py
opps/articles/search_indexes.py
opps/articles/signals.py
opps/articles/urls.py
opps/articles/utils.py
opps/articles/views.py
opps/articles/migrations/0001_initial.py
opps/articles/migrations/__init__.py
opps/articles/templates/articles/album_detail.html
opps/articles/templates/articles/album_list.html
opps/articles/templates/articles/article_tags.html
opps/articles/templates/articles/articlebox_container_list.html
opps/articles/templates/articles/articlebox_detail.html
opps/articles/templates/articles/articlebox_list.html
opps/articles/templates/articles/feed_item_description.html
opps/articles/templates/articles/post_detail.html
opps/articles/templates/articles/post_list.html
opps/articles/templates/articles/album/list.html
opps/articles/templates/search/search.html
opps/articles/templates/search/indexes/articles/album_text.txt
opps/articles/templates/search/indexes/articles/link_text.txt
opps/articles/templates/search/indexes/articles/post_text.txt
opps/bin/__init__.py
opps/bin/opps-admin.py
opps/boxes/__init__.py
opps/boxes/admin.py
opps/boxes/forms.py
opps/boxes/models.py
opps/boxes/migrations/0001_initial.py
opps/boxes/migrations/0002_auto__add_field_queryset_offset.py
opps/boxes/migrations/0003_auto__add_field_queryset_order_field.py
opps/boxes/migrations/0004_auto__add_field_queryset_excludes.py
