Metadata-Version: 1.1
Name: opps
Version: 0.2.13
Summary: Open Source Content Management Platform - CMS for the 
Home-page: http://oppsproject.org
Author: Thiago Avelino
Author-email: thiago@avelino.xxx
License: MIT
Download-URL: https://github.com/opps/opps/tarball/master
Keywords: opps cms django apps magazines websites
Platform: UNKNOWN
Classifier: Development Status :: 5 - Production/Stable
Classifier: Environment :: Web Environment
Classifier: Intended Audience :: Developers
Classifier: License :: OSI Approved :: MIT License
Classifier: Operating System :: OS Independent
Classifier: Framework :: Django
Classifier: Framework :: Opps
Classifier: Programming Language :: Python
Classifier: Programming Language :: Python :: 2.7
Classifier: Operating System :: OS Independent
Classifier: Topic :: Internet :: WWW/HTTP :: Dynamic Content
Classifier: Topic :: Software Development :: Libraries :: Application Frameworks
Classifier: Topic :: Software Development :: Libraries :: Python Modules
